llama_index/embeddings/fireworks/__init__.py
llama_index/embeddings/fireworks/base.py
llama_index/embeddings/fireworks/utils.py
llama_index_embeddings_fireworks-0.4.2.dist-info/METADATA
llama_index_embeddings_fireworks-0.4.2.dist-info/WHEEL
llama_index_embeddings_fireworks-0.4.2.dist-info/licenses/LICENSE
llama_index_embeddings_fireworks-0.4.2.dist-info/RECORD
